sahayak/__init__.py
sahayak/common/__init__.py
sahayak/common/embeddings.py
sahayak/common/util.py
sahayak/docbot/__init__.py
sahayak/docbot/bot.py
sahayak/docbot/create_index.py
sahayak/raahiAI/__init__.py
sahayak/raahiAI/models.py
sahayak/raahiAI/prompts.py
sahayak/raahiAI/raahi.py
tests/__init__.py
tests/test_raahi.py
sahayakAI-0.0.1.dist-info/METADATA
sahayakAI-0.0.1.dist-info/WHEEL
sahayakAI-0.0.1.dist-info/top_level.txt
sahayakAI-0.0.1.dist-info/RECORD
