Metadata-Version: 2.1
Name: sahayakAI
Version: 0.0.1
Summary: Sahayak toolkit for India specif use cases
Home-page: https://github.com/PandoraaBox/sahayakAI
Author: PandoraaBox
Author-email: sahayak@pandoraabox.com
License: PandoraaBox Internal
Requires-Dist: pydantic
Requires-Dist: requests
Requires-Dist: simpleaichat
Requires-Dist: python-telegram-bot
Requires-Dist: pyyaml
Requires-Dist: fastapi
Requires-Dist: uvicorn[standard]
